auto_removable_pathlib/__init__.py
auto_removable_pathlib/auto_removable_path.py
auto_removable_pathlib-0.0.7.dist-info/LICENSE
auto_removable_pathlib-0.0.7.dist-info/METADATA
auto_removable_pathlib-0.0.7.dist-info/WHEEL
auto_removable_pathlib-0.0.7.dist-info/top_level.txt
auto_removable_pathlib-0.0.7.dist-info/RECORD
